as_dynamodb/__init__.py
as_dynamodb/deserialize.py
as_dynamodb/discover.py
as_dynamodb/dynamodb.py
as_dynamodb/sync.py
as_dynamodb/sync_strategies/__init__.py
as_dynamodb/sync_strategies/full_table.py
as_dynamodb/sync_strategies/log_based.py
dz_dynamodb/__init__.py
dz_dynamodb/deserialize.py
dz_dynamodb/discover.py
dz_dynamodb/dynamodb.py
dz_dynamodb/sync.py
dz_dynamodb/sync_strategies/__init__.py
dz_dynamodb/sync_strategies/full_table.py
dz_dynamodb/sync_strategies/log_based.py
as_dynamodb-1.3.9.dist-info/LICENSE
as_dynamodb-1.3.9.dist-info/METADATA
as_dynamodb-1.3.9.dist-info/WHEEL
as_dynamodb-1.3.9.dist-info/entry_points.txt
as_dynamodb-1.3.9.dist-info/top_level.txt
as_dynamodb-1.3.9.dist-info/RECORD
